Workbook

Sheet Read Me
A1: Little Acres - Balance Sheet v2
A2: Purpose: single source of truth for economy numbers. On approval, values export into src/data/ (crops.ts, levels.ts, orders.ts, decor.ts, quests.ts).
A3: Regenerated 2026-07-13 (original v2 delivered 2026-07-12; this copy is identical in blessed values). Save as docs/balance-v2.xlsx.
A5: LEGEND
A6: Blue text = v2 values (blessed 2026-07-12): Dewmelon, Sagesprig, L7/L8 thresholds, their unit caps. Black = shipped values from src/data. Green = pulls live from another sheet.
A7: Every derived column is a live formula - change a blue cell and the audits recompute.
A9: WHAT V2 ADDS OVER V1
A10: 1. Crops sheet: Dewmelon (L7) and Sagesprig (L8) - wave 2, task T3.11. Long crops keep the v1 rule: plateau near 5 coins/min so active play stays best paid.
A11: 2. Levels sheet: cap 6 -> 8; thresholds L7 3500, L8 5500.
A12: 3. Decor sheet: the 10 shop prices + 5 quest trophies (shipped in T3.9, source decor.ts).
A13: 4. Quests sheet: 7 long quests + 4 weekly quests (shipped in T3.10, source quests.ts). NOTE: Weekly Growth is grow-minutes based - the count-based weekly in the first v2 draft was redesigned after the sunwheat-spam flaw was caught; quests.ts is the source of truth.
A15: CASCADES TO FLAG
... A17: Seed bar goes 5 -> 7 buttons (T3.11 includes the measured refit + WYWA/Inventory 7-row fit check).

Sheet Crops
A1: Crop economy - shipped (black) + T3.11 additions (blue)
A3: Crop | B3: Unlock Lv | C3: Grow (s) | D3: Grow (min) | E3: Seed cost | F3: Sell value | G3: XP/harvest | H3: Profit/cycle | I3: Coins/min/plot | J3: XP/min/plot | K3: Cycles/hr | L3: Niche
A4: Sunwheat | B4: 1 | C4: 30 | D4: =C4/60 -> 0.5 | E4: 5 | F4: 8 | G4: 2 | H4: =F4-E4 -> 3 | I4: =H4/D4 -> 6 | J4: =G4/D4 -> 4 | K4: =60/D4 -> 120 | L4: Active coins/min king
A5: Starcorn | B5: 2 | C5: 120 | D5: =C5/60 -> 2 | E5: 12 | F5: 20 | G5: 9 | H5: =F5-E5 -> 8 | I5: =H5/D5 -> 4 | J5: =G5/D5 -> 4.5 | K5: =60/D5 -> 30 | L5: XP king: 4.5 xp/min
A6: Glowberry | B6: 3 | C6: 300 | D6: =C6/60 -> 5 | E6: 30 | F6: 55 | G6: 15 | H6: =F6-E6 -> 25 | I6: =H6/D6 -> 5 | J6: =G6/D6 -> 3 | K6: =60/D6 -> 12 | L6: Payload + order value
A7: Moonroot | B7: 4 | C7: 480 | D7: =C7/60 -> 8 | E7: 60 | F7: 100 | G7: 28 | H7: =F7-E7 -> 40 | I7: =H7/D7 -> 5 | J7: =G7/D7 -> 3.5 | K7: =60/D7 -> 7.5 | L7: Half-session crop, 8 min
A8: Emberpepper | B8: 5 | C8: 1200 | D8: =C8/60 -> 20 | E8: 110 | F8: 210 | G8: 70 | H8: =F8-E8 -> 100 | I8: =H8/D8 -> 5 | J8: =G8/D8 -> 3.5 | K8: =60/D8 -> 3 | L8: Leave-and-return, 20 min
A9: Dewmelon | B9: 7 | C9: 2700 | D9: =C9/60 -> 45 | E9: 260 | F9: 500 | G9: 150 | H9: =F9-E9 -> 240 | I9: =H9/D9 -> 5.3333333 | J9: =G9/D9 -> 3.3333333 | K9: =60/D9 -> 1.3333333 | L9: NEW L7 (T3.11): session-bridging 45 min, big payload
A10: Sagesprig | B10: 8 | C10: 7200 | D10: =C10/60 -> 120 | E10: 600 | F10: 1200 | G10: 400 | H10: =F10-E10 -> 600 | I10: =H10/D10 -> 5 | J10: =G10/D10 -> 3.3333333 | K10: =60/D10 -> 0.5 | L10: NEW L8 (T3.11): overnight/2h prestige crop, biggest payload
A12: Blue = T3.11 additions (blessed 2026-07-12). Black = shipped values from crops.ts.
A13: Audit: no crop tops BOTH Coins/min and XP/min. Long-crop rule: coins/min plateaus near 5 (Dewmelon 5.33, Sagesprig 5.0).

Sheet Levels
A1: Level curve - cap 8 (v2)
A3: Level | B3: XP threshold | C3: Delta xp | D3: Unlock
A4: 1 | B4: 0 | C4: 0 | D4: start (Sunwheat)
A5: 2 | B5: 30 | C5: =B5-B4 -> 30 | D5: Starcorn
A6: 3 | B6: 90 | C6: =B6-B5 -> 60 | D6: Glowberry
A7: 4 | B7: 450 | C7: =B7-B6 -> 360 | D7: Moonroot
A8: 5 | B8: 1000 | C8: =B8-B7 -> 550 | D8: Emberpepper
A9: 6 | B9: 2000 | C9: =B9-B8 -> 1000 | D9: Chests
A10: 7 | B10: 3500 | C10: =B10-B9 -> 1500 | D10: Dewmelon (NEW)
A11: 8 | B11: 5500 | C11: =B11-B10 -> 2000 | D11: Sagesprig (NEW)
A13: Thresholds 1-6 shipped (levels.ts). L7/L8 blessed 2026-07-12. No migration: stored level only ever increases (T1.7).

Sheet Orders & Sanity
A1: Order rewards + unit caps
A3: Reward multipliers (orders.ts, shipped)
A4: Coin multiplier x sell | B4: 1.3
A5: XP multiplier x crop xp | B5: 1.5
A7: Crop | B7: Order coins/unit | C7: Order xp/unit | D7: Unit cap
A8: =Crops!A4 -> Sunwheat | B8: =Crops!F4*$B$4 -> 10.4 | C8: =Crops!G4*$B$5 -> 3 | D8: -
A9: =Crops!A5 -> Starcorn | B9: =Crops!F5*$B$4 -> 26 | C9: =Crops!G5*$B$5 -> 13.5 | D9: 5
A10: =Crops!A6 -> Glowberry | B10: =Crops!F6*$B$4 -> 71.5 | C10: =Crops!G6*$B$5 -> 22.5 | D10: 2
A11: =Crops!A7 -> Moonroot | B11: =Crops!F7*$B$4 -> 130 | C11: =Crops!G7*$B$5 -> 42 | D11: 3
A12: =Crops!A8 -> Emberpepper | B12: =Crops!F8*$B$4 -> 273 | C12: =Crops!G8*$B$5 -> 105 | D12: 2
A13: =Crops!A9 -> Dewmelon | B13: =Crops!F9*$B$4 -> 650 | C13: =Crops!G9*$B$5 -> 225 | D13: 2
A14: =Crops!A10 -> Sagesprig | B14: =Crops!F10*$B$4 -> 1560 | C14: =Crops!G10*$B$5 -> 600 | D14: 1
A16: Green = pulls live from the Crops sheet. Caps keep one order from demanding more than a plot-capped field can hold; blue caps blessed with T3.11.

Sheet Decor
A1: Decorations - shipped T3.9 (decor.ts)
A3: Item | B3: Currency | C3: Price
A4: Bench | B4: coins | C4: 400
A5: Flowerbed | B5: coins | C5: 600
A6: Fence | B6: coins | C6: 250
A7: Barrels | B7: coins | C7: 350
A8: Scarecrow | B8: coins | C8: 900
A9: Birdbath | B9: coins | C9: 1200
A10: Well | B10: coins | C10: 2000
A11: Mushrooms | B11: moondust | C11: 4
A12: Gnome | B12: moondust | C12: 6
A13: Lantern | B13: moondust | C13: 8
A15: Trophies (not purchasable; quest rewards, T3.10)
A16: trophy_goldscarecrow (Golden Fields)
A17: trophy_starbanner (Star Farmer)
A18: trophy_moonwell (Keeper of the Glow)
A19: trophy_traderscart (Premium Partner)
A20: trophy_ancientoak (Deep Roots)
A22: Cap: 30 owned total (placed + warehoused, checked at purchase). Moondust items are THE moondust sink.

Sheet Quests
A1: Quests - shipped T3.10 (quests.ts is the source of truth)
A3: LONG QUESTS (lifetime counters)
A4: Quest | B4: Counter | C4: Target | D4: Reward
A5: Golden Fields | B5: Sunwheat harvests | C5: 500 | D5: trophy_goldscarecrow
A6: Star Farmer | B6: Starcorn harvests | C6: 300 | D6: trophy_starbanner
A7: Keeper of the Glow | B7: Glowberry harvests | C7: 200 | D7: trophy_moonwell
A8: Village Favorite | B8: Orders fulfilled | C8: 50 | D8: 2 chests
A9: Premium Partner | B9: Premium orders fulfilled | C9: 25 | D9: trophy_traderscart
A10: Treasure Hunter | B10: Chests opened | C10: 10 | D10: 3 chests
A11: Deep Roots | B11: Total harvests (any crop) | C11: 2000 | D11: trophy_ancientoak
A13: WEEKLY QUESTS (real-clock weekly reset; 2 of 4 active per week)
A14: Quest | B14: Counter | C14: Target | D14: Reward
A15: Growing Strong | B15: Grow-minutes harvested (sum of grow time) | C15: 400 | D15: 1 chest
A16: Specialist | B16: Featured-crop harvests (tiered, below) | C16: per crop | D16: 1 chest + 2 moondust
A17: Weekly Trader | B17: Orders fulfilled | C17: 12 | D17: 3 moondust
A18: Weekly Radiance | B18: Radiant crops harvested | C18: 2 | D18: 1 chest
A20: Specialist per-crop targets: Sunwheat 60 / Starcorn 25 / Glowberry 15 / Moonroot 12 / Emberpepper 8
A21: Design note: Growing Strong is grow-minutes based (not harvest counts) so it cannot be sunwheat-spammed; blessed with the v2 sheet 2026-07-12.
A22: T3.11 follow-up: decide Dewmelon/Sagesprig Specialist tiers when the crops ship (suggest 6 / 3 by grow-time ratio).
